gem/__about__.py
gem/__init__.py
gem/core.py
gem/envs/__init__.py
gem/envs/code_env.py
gem/envs/math_env.py
gem/envs/qa_env.py
gem/envs/reasoning_gym.py
gem/envs/registration.py
gem/envs/game_env/README.md
gem/envs/game_env/__init__.py
gem/envs/game_env/fifteen_puzzle.py
gem/envs/game_env/guess_the_number.py
gem/envs/game_env/hangman.py
gem/envs/game_env/mastermind.py
gem/envs/game_env/minesweeper.py
gem/envs/game_env/sudoku.py
gem/envs/game_env/tower_of_hanoi.py
gem/envs/game_env/wordle.py
gem/envs/terminal/README.md
gem/envs/terminal/docker_env.py
gem/envs/terminal/executor.py
gem/envs/terminal/reward.py
gem/tools/base_tool.py
gem/tools/python_code_tool.py
gem/tools/search_tool.py
gem/tools/tool_env_wrapper.py
gem/tools/search_engine/google_search_server.py
gem/tools/search_engine/retrieval_server.py
gem/tools/search_engine/serp_search_server.py
gem/utils/constants.py
gem/utils/debug.py
gem/utils/parsing.py
gem/utils/qa_em.py
gem/utils/sandbox.py
gem/utils/seeding.py
gem/vector/async_vector_env.py
gem/vector/sync_vector_env.py
gem/vector/vector_env.py
gem/wrappers/episode_tracking_wrapper.py
gem/wrappers/observation_wrapper.py
gem/wrappers/wrapper_factory.py
gem_llm-0.0.4.dist-info/LICENSE.txt
gem_llm-0.0.4.dist-info/METADATA
gem_llm-0.0.4.dist-info/WHEEL
gem_llm-0.0.4.dist-info/top_level.txt
gem_llm-0.0.4.dist-info/RECORD
